Workbook

Sheet README
B1: GoPro x Sidemen – Partnership Value Model
B2: Independent, unsolicited proposal prepared by Sino Lam · Built from public data · Not affiliated with or endorsed by Sidemen, GoPro or Upside · All money in £ unless stated
B4: What this model answers
B5: 1. Which brand should the Sidemen approach? (Scorecard – ten candidate brands scored on six weighted criteria)
B6: 2. What is a GoPro partnership worth? (Deal_Value – media value of each asset, plus GoPro camera sales through a Sidemen code)
B7: 3. How should the deal be structured for a brand in recovery? (Deal_Structure – fixed fee, product and sales commission; value to each side)
B8: 4. Which assumptions matter most? (Sensitivity – one-way tornado and low / base / high scenarios)
B9: 5. Which Upside portfolio companies should get Sidemen airtime, and how? (Upside – same scorecard, plus value created per £ of airtime)
B11: Method
B12: Media value = views × cost per 1,000 views (CPM) that a brand would otherwise pay. Event placements are adjusted for how prominent the brand is in the stream and given a premium for exclusivity and live reach.
B13: Sales = long-form and event views × share who click the Sidemen link or code × share who buy × average order value. Only incremental sales (buyers who would not have bought anyway) count towards GoPro's gross profit.
B14: Value to GoPro per £1 = (media value + incremental gross profit) ÷ (fixed fee + product + commission). Above 1.0 means GoPro gets more value than it pays.
... B22: • Upside figures (value per customer, conversion) are illustrative assumptions to show the method; they would be replaced with each company's own data.

Sheet Summary
A1: GoPro x Sidemen – Summary
A2: Independent, unsolicited proposal by Sino Lam · 12-month partnership built around the next Sidemen Charity Match
A4: Headline | B4: Value
A5: Top-ranked brand on the scorecard | B5: =INDEX(Scorecard!A5:A15,MATCH(1,Scorecard!J5:J15,0)) -> GoPro
A6: GoPro weighted fit score (out of 5) | B6: =Scorecard!H5 -> 4.55
A7: Total views delivered (m) | B7: =Deal_Value!D9 -> 72.5
A8: Media value of the package (£k) | B8: =Deal_Value!H9 -> 835.5
A9: Cameras sold through Sidemen code | B9: =Deal_Value!B15 -> 2220
A10: Code sales revenue (£k) | B10: =Deal_Value!B16 -> 666
A11: Total cost to GoPro (£k) | B11: =Deal_Structure!B8 -> 456.6
A12: Value to GoPro per £1 (base) | B12: =Deal_Structure!B16 -> 2.1728936
A13: Value to GoPro per £1 (low scenario) | B13: =Deal_Structure!B33 -> 0.8130184
A14: Value to GoPro per £1 (high scenario) | B14: =Deal_Structure!D33 -> 3.6964037
A15: Sidemen cash income (£k) | B15: =Deal_Structure!B19 -> 416.6
A16: Deal cost as % of GoPro's 2025 sales & marketing | B16: =Deal_Structure!B20 -> 0.0060396825
A17: Upside priority company | B17: =INDEX(Upside!B4:D4,MATCH(MAX(Upside!B16:D16),Upside!B16:D16,0)) -> Howbout

Sheet Scorecard
A1: Brand-fit scorecard: who should the Sidemen approach?
A2: Scores 1 (poor) to 5 (excellent) are the author's judgement; weights (blue) can be changed. Excluded up front: brands that clash with Sidemen-owned or member-owned businesses, existing partners, and categories with negative audience sentiment.
B3: Audience fit (18-25, UK) | C3: Fits naturally in videos and events | D3: No clash with Sidemen or member brands | E3: Freshness: not overused by UK creators | F3: Brand safety and sentiment | G3: Commercial need: why now | H3: Weighted score (out of 5) | I3: Score % | J3: Rank | K3: Main reason
A4: Weight | B4: 0.2 | C4: 0.25 | D4: 0.15 | E4: 0.15 | F4: 0.1 | G4: 0.15 | H4: =SUM(B4:G4) -> 1
A5: GoPro | B5: 4 | C5: 5 | D5: 5 | E5: 4 | F5: 4 | G5: 5 | H5: =SUMPRODUCT($B$4:$G$4,B5:G5) -> 4.55 | I5: =H5/5 -> 0.91 | J5: =RANK(H5,$H$5:$H$15) -> 1 | K5: The product films the content itself; already appears organically: players such as WillNE and Miniminter have brought their own GoPros to the Charity Match as unsponsored 'player cams'; revenue down 18.7% and marketing cut 37%, so it needs efficient reach to young buyers.
A6: PlayStation | B6: 5 | C6: 4 | D6: 5 | E6: 2 | F6: 4 | G6: 4 | H6: =SUMPRODUCT($B$4:$G$4,B6:G6) -> 4.05 | I6: =H6/5 -> 0.81 | J6: =RANK(H6,$H$5:$H$15) -> 2 | K6: Strong gaming heritage and GTA 6 launch timing; already works with many gaming creators; depends on Sony's sponsor policy.
A7: IKEA | B7: 3 | C7: 4 | D7: 5 | E7: 4 | F7: 5 | G7: 3 | H7: =SUMPRODUCT($B$4:$G$4,B7:G7) -> 3.9 | I7: =H7/5 -> 0.78 | J7: =RANK(H7,$H$5:$H$15) -> 3 | K7: Fun build-off formats and Sidemen house content; safe brand; less obvious reason to spend now.
A8: Virgin Atlantic | B8: 3 | C8: 4 | D8: 5 | E8: 4 | F8: 4 | G8: 3 | H8: =SUMPRODUCT($B$4:$G$4,B8:G8) -> 3.8 | I8: =H8/5 -> 0.76 | J8: =RANK(H8,$H$5:$H$15) -> 5 | K8: Economy vs Upper Class challenges and US trips; premium price for 18-25s.
A9: Merlin (Thorpe Park) | B9: 4 | C9: 4 | D9: 5 | E9: 3 | F9: 4 | G9: 3 | H9: =SUMPRODUCT($B$4:$G$4,B9:G9) -> 3.85 | I9: =H9/5 -> 0.77 | J9: =RANK(H9,$H$5:$H$15) -> 4 | K9: Theme-park challenges and fan experiences suit the format; seasonal, and theme parks appear regularly in UK creator content.
A10: Airbnb | B10: 4 | C10: 4 | D10: 5 | E10: 3 | F10: 3 | G10: 3 | H10: =SUMPRODUCT($B$4:$G$4,B10:G10) -> 3.75 | I10: =H10/5 -> 0.75 | J10: =RANK(H10,$H$5:$H$15) -> 6 | K10: Cheap vs luxury stays; widely used by creators; mixed public sentiment in the UK.
A11: STATSports | B11: 2 | C11: 4 | D11: 5 | E11: 5 | F11: 5 | G11: 2 | H11: =SUMPRODUCT($B$4:$G$4,B11:G11) -> 3.7 | I11: =H11/5 -> 0.74 | J11: =RANK(H11,$H$5:$H$15) -> 7 | K11: Original Charity Match data story, but a niche product with little consumer reach.
A12: Monopoly (board game) | B12: 3 | C12: 5 | D12: 5 | E12: 2 | F12: 4 | G12: 2 | H12: =SUMPRODUCT($B$4:$G$4,B12:G12) -> 3.6 | I12: =H12/5 -> 0.72 | J12: =RANK(H12,$H$5:$H$15) -> 8 | K12: Game-show format fits perfectly, but Monopoly GO! (a separate mobile game) sponsors many creators and fans may confuse the two.
A13: Duolingo | B13: 5 | C13: 3 | D13: 5 | E13: 1 | F13: 3 | G13: 4 | H13: =SUMPRODUCT($B$4:$G$4,B13:G13) -> 3.55 | I13: =H13/5 -> 0.71 | J13: =RANK(H13,$H$5:$H$15) -> 9 | K13: Proven with this audience (Chunkz and Yung Filly, 2023), so not fresh; 2025 'AI-first' backlash.
A14: Whoop | B14: 3 | C14: 4 | D14: 5 | E14: 2 | F14: 4 | G14: 3 | H14: =SUMPRODUCT($B$4:$G$4,B14:G14) -> 3.5 | I14: =H14/5 -> 0.7 | J14: =RANK(H14,$H$5:$H$15) -> 10 | K14: Good Charity Match data angle; premium subscription; sponsors many podcasts.
A15: Garmin | B15: 2 | C15: 3 | D15: 5 | E15: 4 | F15: 5 | G15: 2 | H15: =SUMPRODUCT($B$4:$G$4,B15:G15) -> 3.3 | I15: =H15/5 -> 0.66 | J15: =RANK(H15,$H$5:$H$15) -> 11 | K15: Safe and conflict-free, but skews older and endurance-focused.

Sheet Inputs
A1: Inputs and assumptions
A2: Low / Base / High feed the Sensitivity sheet. Change blue values; everything else updates.
A4: ID | B4: Input | C4: Unit | D4: Low | E4: Base | F4: High | G4: Type | H4: Source / reasoning
A5: Audience (public data)
A6: MV | B6: Sidemen main-channel views per video (recent median) | C6: m views | D6: 6 | E6: 8.5 | F6: 12 | G6: Derived | H6: OutlierKit lists recent outliers at 2.4× and 1.5× the recent median (20.0m and 13.0m views), implying a median of c.8.3-8.7m. vidIQ: 23.4m subscribers, 51.9m views in the last 28 days (Oct 2026).
A7: CMV | B7: Charity Match stream views | C7: m views | D7: 8 | E7: 11 | F7: 14 | G7: Sourced | H7: 2026 match (18 Apr 2026, Wembley): over 11m YouTube views, peak 2.2m concurrent viewers, £6.2m raised (Tubefilter, Apr 2026). 2025 match drew over 14m views, so the range spans both years.
A8: Deal package (proposal design)
A9: NV | B9: GoPro-filmed main-channel videos | C9: videos | E9: 3 | G9: Proposal | H9: Three Sidemen Sunday challenges filmed on GoPro point-of-view cameras, with a natural mention and pinned link.
A10: EPF | B10: GoPro prominence in Charity Match stream | C10: share | D10: 0.3 | E10: 0.5 | F10: 0.7 | G10: Assumption | H10: 'Player Cam powered by GoPro' and goal replays are one of several on-screen elements, so only part of the stream's value is credited.
A11: EPP | B11: Event premium for exclusivity, live reach and press | C11: multiple | D11: 1 | E11: 1.5 | F11: 2 | G11: Assumption | H11: Tentpole events command a premium over standard video rates: live audience, exclusivity in the category and coverage beyond YouTube.
A12: SC | B12: Short-form clips (TikTok, Shorts, Instagram) | C12: clips | E12: 20 | G12: Proposal | H12: POV highlight clips cut from the videos and match.
A13: SV | B13: Views per short-form clip | C13: m views | D13: 0.8 | E13: 1.5 | F13: 2.5 | G13: Assumption | H13: Analyst assumption for Sidemen short-form clips; replace with channel analytics.
A14: BC | B14: Behind-the-scenes vlogs (second channel) | C14: videos | E14: 2 | G14: Proposal | H14: Kit-up and match-day vlogs.
A15: BV | B15: Views per behind-the-scenes vlog | C15: m views | D15: 2 | E15: 3 | F15: 4 | G15: Assumption | H15: Analyst assumption for second-channel vlogs; replace with channel analytics.
A16: Pricing
A17: FX | B17: Exchange rate (£ per US$) | C17: £/$ | E17: 0.75 | G17: Assumption | H17: Approximate rate used to convert US benchmarks.
A18: CPMU | B18: Long-form sponsorship CPM (US$ per 1,000 views) | C18: $ | D18: 15 | E18: 24 | F18: 30 | G18: Sourced | H18: Influencer Marketing Hub: YouTube sponsorship CPMs generally $15-30 (2025-26). Upper half used for base: UK, 18-25, highly engaged mega-creator.
A19: CPML | B19: Long-form CPM in £ | C19: £ | E19: =E18*E17 -> 18 | G19: Derived | H19: US$ CPM × exchange rate.
A20: CPMS | B20: Short-form CPM (£ per 1,000 views) | C20: £ | D20: 2 | E20: 4 | F20: 6 | G20: Assumption | H20: Short-form views are cheaper: shorter attention and lower completion.
A21: Sales through the Sidemen code
A22: CTR | B22: Share of long-form/event views who visit via link or code | C22: % | D22: 0.001 | E22: 0.002 | F22: 0.004 | G22: Assumption | H22: Typical creator link click-through for an integrated (not dedicated) mention.
A23: CVR | B23: Share of visitors who buy | C23: % | D23: 0.02 | E23: 0.03 | F23: 0.05 | G23: Assumption | H23: E-commerce conversion for warm, creator-referred traffic.
A24: AOV | B24: Average order value | C24: £ | D24: 250 | E24: 300 | F24: 400 | G24: Sourced | H24: PriceSpy: HERO13 Black from £268.64; retail listings around £400. Base allows for discount codes and older models.
A25: GM | B25: GoPro gross margin | C25: % | E25: 0.336 | G25: Sourced | H25: GoPro FY2025 GAAP gross margin 33.6% (Q4/FY2025 results, Mar 2026).
A26: INC | B26: Share of code sales that are incremental | C26: % | D26: 0.5 | E26: 0.7 | F26: 0.9 | G26: Assumption | H26: Some buyers would have bought a GoPro anyway.
A27: Proposed deal terms
A28: FEE | B28: Fixed partnership fee (12 months) | C28: £k | E28: 350 | G28: Proposal | H28: Set at roughly 40% of estimated media value: low fixed cost for a brand cutting marketing spend, with upside paid through commission.
A29: PROD | B29: Product and kit supplied | C29: £k | E29: 40 | G29: Proposal | H29: Cameras, mounts and accessories for members, crew and match-day player cams.
A30: COM | B30: Commission on code sales | C30: % | E30: 0.1 | G30: Proposal | H30: Performance element: Sidemen earn more only if GoPro sells more.
A31: GoPro context (for scale)
A32: REV | B32: GoPro FY2025 revenue | C32: $m | E32: 651.5 | G32: Sourced | H32: GoPro Q4 and FY2025 results: revenue $651.5m, down 18.7%.
A33: SM | B33: GoPro FY2025 sales & marketing expense | C33: $m | E33: 100.8 | G33: Sourced | H33: GoPro FY2025 results: S&M $100.8m vs $160.6m in 2024. 10-K: marketing spend cut 37%.

Sheet Deal_Value
A1: What a 12-month GoPro partnership is worth
A2: Media value is what GoPro would otherwise pay for the same attention. All values £k.
A4: Asset | B4: Units | C4: Views per unit (m) | D4: Total views (m) | E4: CPM (£) | F4: Prominence | G4: Event premium | H4: Media value (£k) | I4: Share
A5: GoPro-filmed Sidemen Sunday challenges | B5: =Inputs!$E$9 -> 3 | C5: =Inputs!$E$6 -> 8.5 | D5: =B5*C5 -> 25.5 | E5: =Inputs!$E$19 -> 18 | F5: 1 | G5: 1 | H5: =D5*E5*F5*G5 -> 459 | I5: =H5/$H$9 -> 0.54937163
A6: Charity Match: 'Player Cam powered by GoPro' | B6: 1 | C6: =Inputs!$E$7 -> 11 | D6: =B6*C6 -> 11 | E6: =Inputs!$E$19 -> 18 | F6: =Inputs!$E$10 -> 0.5 | G6: =Inputs!$E$11 -> 1.5 | H6: =D6*E6*F6*G6 -> 148.5 | I6: =H6/$H$9 -> 0.17773788
A7: Short-form POV clips | B7: =Inputs!$E$12 -> 20 | C7: =Inputs!$E$13 -> 1.5 | D7: =B7*C7 -> 30 | E7: =Inputs!$E$20 -> 4 | F7: 1 | G7: 1 | H7: =D7*E7*F7*G7 -> 120 | I7: =H7/$H$9 -> 0.14362657
A8: Behind-the-scenes vlogs | B8: =Inputs!$E$14 -> 2 | C8: =Inputs!$E$15 -> 3 | D8: =B8*C8 -> 6 | E8: =Inputs!$E$19 -> 18 | F8: 1 | G8: 1 | H8: =D8*E8*F8*G8 -> 108 | I8: =H8/$H$9 -> 0.12926391
A9: Total media value | D9: =SUM(D5:D8) -> 72.5 | H9: =SUM(H5:H8) -> 835.5 | I9: =SUM(I5:I8) -> 1
A12: Camera sales through the Sidemen code
A13: Views that can drive sales (long-form + event, prominence-adjusted), m | B13: =D5+D6*F6+D8 -> 37
A14: Visitors via link or code | B14: =B13*1000000*Inputs!$E$22 -> 74000
A15: Buyers | B15: =B14*Inputs!$E$23 -> 2220
A16: Code sales revenue (£k) | B16: =B15*Inputs!$E$24/1000 -> 666
A17: Incremental revenue (£k) | B17: =B16*Inputs!$E$26 -> 466.2
A18: Incremental gross profit to GoPro (£k) | B18: =B17*Inputs!$E$25 -> 156.6432
A21: Check: media value matches closed-form formula (should be 0) | B21: =ROUND(H9-(Inputs!$E$9*Inputs!$E$6*Inputs!$E$18*Inputs!$E$17+Inputs!$E$7*Inputs!$E$18*Inputs!$E$17*Inputs!$E$11*Inputs!$E$10+Inputs!$E$12*Inputs!$E$13*Inputs!$E$20+Inputs!$E$14*Inputs!$E$15*Inputs!$E$18*Inputs!$E$17),6) -> 0
A22: Check: code revenue matches closed-form formula (should be 0) | B22: =ROUND(B16-((Inputs!$E$9*Inputs!$E$6+Inputs!$E$7*Inputs!$E$10+Inputs!$E$14*Inputs!$E$15)*1000*Inputs!$E$22*Inputs!$E$23*Inputs!$E$24),6) -> 0

Sheet Deal_Structure
A1: Deal structure: built for a brand in recovery
A2: Low fixed fee + product + commission on sales. GoPro only pays more when the partnership sells more cameras.
A4: GoPro pays | B4: £k | C4: Notes
A5: Fixed partnership fee | B5: =Inputs!$E$28 -> 350 | C5: Paid in instalments: signing, Charity Match, final video
A6: Product and kit | B6: =Inputs!$E$29 -> 40 | C6: Valued at retail; low cash cost to GoPro
A7: Commission on code sales | B7: =Inputs!$E$30*Deal_Value!B16 -> 66.6 | C7: Performance element
A8: Total cost to GoPro | B8: =SUM(B5:B7) -> 456.6
A10: GoPro receives | B10: £k | C10: Notes
A11: Media value of Sidemen content | B11: =Deal_Value!H9 -> 835.5 | C11: What the same attention would cost elsewhere
A12: Incremental gross profit on code sales | B12: =Deal_Value!B18 -> 156.6432 | C12: Only sales that would not have happened anyway
A13: Total value to GoPro | B13: =SUM(B11:B12) -> 992.1432
A15: Key results | B15: Value | C15: What it means
A16: Value to GoPro per £1 spent | B16: =B13/B8 -> 2.1728936 | C16: Above 1.0x: GoPro gets more than it pays
A17: Fixed fee as % of media value | B17: =B5/B11 -> 0.41891083 | C17: A discount to market rate in exchange for performance upside
A18: Code sales: gross profit covers what share of GoPro's cost | B18: =B12/B8 -> 0.34306439 | C18: Direct payback before counting brand value
A19: Sidemen cash income (fee + commission) | B19: =B5+B7 -> 416.6 | C19: Plus product for content
A20: Deal cost as % of GoPro's annual S&M budget | B20: =B8/(Inputs!$E$33*1000*Inputs!$E$17) -> 0.0060396825 | C20: Small, testable spend for GoPro
A21: Cameras sold through the code | B21: =Deal_Value!B15 -> 2220 | C21: Trackable outcome
A22: Effective cost per 1,000 views (all assets) | B22: =B8/Deal_Value!D9 -> 6.297931 | C22: Compare: long-form market CPM on Inputs
A24: Check: value per £1 matches closed-form formula (should be 0) | B24: =ROUND(B16-((Inputs!$E$9*Inputs!$E$6*Inputs!$E$18*Inputs!$E$17+Inputs!$E$7*Inputs!$E$18*Inputs!$E$17*Inputs!$E$11*Inputs!$E$10+Inputs!$E$12*Inputs!$E$13*Inputs!$E$20+Inputs!$E$14*Inputs!$E$15*Inputs!$E$18*Inputs!$E$17)+((Inputs!$E$9*Inputs!$E$6+Inputs!$E$7*Inputs!$E$10+Inputs!$E$14*Inputs!$E$15)*1000*Inputs!$E$22*Inputs!$E$23*Inputs!$E$24)*Inputs!$E$26*Inputs!$E$25)/(Inputs!$E$28+Inputs!$E$29+Inputs!$E$30*((Inputs!$E$9*Inputs!$E$6+Inputs!$E$7*Inputs!$E$10+Inputs!$E$14*Inputs!$E$15)*1000*Inputs!$E$22*Inputs!$E$23*Inputs!$E$24)),6) -> 0
A27: Scenarios (all uncertain inputs at Low / Base / High)
A28: Result | B28: Low | C28: Base | D28: High
A29: Media value (£k) | B29: =(Inputs!$E$9*Inputs!$D$6*Inputs!$D$18*Inputs!$E$17+Inputs!$D$7*Inputs!$D$18*Inputs!$E$17*Inputs!$D$11*Inputs!$D$10+Inputs!$E$12*Inputs!$D$13*Inputs!$D$20+Inputs!$E$14*Inputs!$D$15*Inputs!$D$18*Inputs!$E$17) -> 306.5 | C29: =(Inputs!$E$9*Inputs!$E$6*Inputs!$E$18*Inputs!$E$17+Inputs!$E$7*Inputs!$E$18*Inputs!$E$17*Inputs!$E$11*Inputs!$E$10+Inputs!$E$12*Inputs!$E$13*Inputs!$E$20+Inputs!$E$14*Inputs!$E$15*Inputs!$E$18*Inputs!$E$17) -> 835.5 | D29: =(Inputs!$E$9*Inputs!$F$6*Inputs!$F$18*Inputs!$E$17+Inputs!$F$7*Inputs!$F$18*Inputs!$E$17*Inputs!$F$11*Inputs!$F$10+Inputs!$E$12*Inputs!$F$13*Inputs!$F$20+Inputs!$E$14*Inputs!$F$15*Inputs!$F$18*Inputs!$E$17) -> 1731
A30: Code sales revenue (£k) | B30: =((Inputs!$E$9*Inputs!$D$6+Inputs!$D$7*Inputs!$D$10+Inputs!$E$14*Inputs!$D$15)*1000*Inputs!$D$22*Inputs!$D$23*Inputs!$D$24) -> 122 | C30: =((Inputs!$E$9*Inputs!$E$6+Inputs!$E$7*Inputs!$E$10+Inputs!$E$14*Inputs!$E$15)*1000*Inputs!$E$22*Inputs!$E$23*Inputs!$E$24) -> 666 | D30: =((Inputs!$E$9*Inputs!$F$6+Inputs!$F$7*Inputs!$F$10+Inputs!$E$14*Inputs!$F$15)*1000*Inputs!$F$22*Inputs!$F$23*Inputs!$F$24) -> 4304
A31: Total value to GoPro (£k) | B31: =((Inputs!$E$9*Inputs!$D$6*Inputs!$D$18*Inputs!$E$17+Inputs!$D$7*Inputs!$D$18*Inputs!$E$17*Inputs!$D$11*Inputs!$D$10+Inputs!$E$12*Inputs!$D$13*Inputs!$D$20+Inputs!$E$14*Inputs!$D$15*Inputs!$D$18*Inputs!$E$17)+((Inputs!$E$9*Inputs!$D$6+Inputs!$D$7*Inputs!$D$10+Inputs!$E$14*Inputs!$D$15)*1000*Inputs!$D$22*Inputs!$D$23*Inputs!$D$24)*Inputs!$D$26*Inputs!$E$25) -> 326.996 | C31: =((Inputs!$E$9*Inputs!$E$6*Inputs!$E$18*Inputs!$E$17+Inputs!$E$7*Inputs!$E$18*Inputs!$E$17*Inputs!$E$11*Inputs!$E$10+Inputs!$E$12*Inputs!$E$13*Inputs!$E$20+Inputs!$E$14*Inputs!$E$15*Inputs!$E$18*Inputs!$E$17)+((Inputs!$E$9*Inputs!$E$6+Inputs!$E$7*Inputs!$E$10+Inputs!$E$14*Inputs!$E$15)*1000*Inputs!$E$22*Inputs!$E$23*Inputs!$E$24)*Inputs!$E$26*Inputs!$E$25) -> 992.1432 | D31: =((Inputs!$E$9*Inputs!$F$6*Inputs!$F$18*Inputs!$E$17+Inputs!$F$7*Inputs!$F$18*Inputs!$E$17*Inputs!$F$11*Inputs!$F$10+Inputs!$E$12*Inputs!$F$13*Inputs!$F$20+Inputs!$E$14*Inputs!$F$15*Inputs!$F$18*Inputs!$E$17)+((Inputs!$E$9*Inputs!$F$6+Inputs!$F$7*Inputs!$F$10+Inputs!$E$14*Inputs!$F$15)*1000*Inputs!$F$22*Inputs!$F$23*Inputs!$F$24)*Inputs!$F$26*Inputs!$E$25) -> 3032.5296
A32: Total cost to GoPro (£k) | B32: =(Inputs!$E$28+Inputs!$E$29+Inputs!$E$30*((Inputs!$E$9*Inputs!$D$6+Inputs!$D$7*Inputs!$D$10+Inputs!$E$14*Inputs!$D$15)*1000*Inputs!$D$22*Inputs!$D$23*Inputs!$D$24)) -> 402.2 | C32: =(Inputs!$E$28+Inputs!$E$29+Inputs!$E$30*((Inputs!$E$9*Inputs!$E$6+Inputs!$E$7*Inputs!$E$10+Inputs!$E$14*Inputs!$E$15)*1000*Inputs!$E$22*Inputs!$E$23*Inputs!$E$24)) -> 456.6 | D32: =(Inputs!$E$28+Inputs!$E$29+Inputs!$E$30*((Inputs!$E$9*Inputs!$F$6+Inputs!$F$7*Inputs!$F$10+Inputs!$E$14*Inputs!$F$15)*1000*Inputs!$F$22*Inputs!$F$23*Inputs!$F$24)) -> 820.4
A33: Value to GoPro per £1 | B33: =((Inputs!$E$9*Inputs!$D$6*Inputs!$D$18*Inputs!$E$17+Inputs!$D$7*Inputs!$D$18*Inputs!$E$17*Inputs!$D$11*Inputs!$D$10+Inputs!$E$12*Inputs!$D$13*Inputs!$D$20+Inputs!$E$14*Inputs!$D$15*Inputs!$D$18*Inputs!$E$17)+((Inputs!$E$9*Inputs!$D$6+Inputs!$D$7*Inputs!$D$10+Inputs!$E$14*Inputs!$D$15)*1000*Inputs!$D$22*Inputs!$D$23*Inputs!$D$24)*Inputs!$D$26*Inputs!$E$25)/(Inputs!$E$28+Inputs!$E$29+Inputs!$E$30*((Inputs!$E$9*Inputs!$D$6+Inputs!$D$7*Inputs!$D$10+Inputs!$E$14*Inputs!$D$15)*1000*Inputs!$D$22*Inputs!$D$23*Inputs!$D$24)) -> 0.8130184 | C33: =((Inputs!$E$9*Inputs!$E$6*Inputs!$E$18*Inputs!$E$17+Inputs!$E$7*Inputs!$E$18*Inputs!$E$17*Inputs!$E$11*Inputs!$E$10+Inputs!$E$12*Inputs!$E$13*Inputs!$E$20+Inputs!$E$14*Inputs!$E$15*Inputs!$E$18*Inputs!$E$17)+((Inputs!$E$9*Inputs!$E$6+Inputs!$E$7*Inputs!$E$10+Inputs!$E$14*Inputs!$E$15)*1000*Inputs!$E$22*Inputs!$E$23*Inputs!$E$24)*Inputs!$E$26*Inputs!$E$25)/(Inputs!$E$28+Inputs!$E$29+Inputs!$E$30*((Inputs!$E$9*Inputs!$E$6+Inputs!$E$7*Inputs!$E$10+Inputs!$E$14*Inputs!$E$15)*1000*Inputs!$E$22*Inputs!$E$23*Inputs!$E$24)) -> 2.1728936 | D33: =((Inputs!$E$9*Inputs!$F$6*Inputs!$F$18*Inputs!$E$17+Inputs!$F$7*Inputs!$F$18*Inputs!$E$17*Inputs!$F$11*Inputs!$F$10+Inputs!$E$12*Inputs!$F$13*Inputs!$F$20+Inputs!$E$14*Inputs!$F$15*Inputs!$F$18*Inputs!$E$17)+((Inputs!$E$9*Inputs!$F$6+Inputs!$F$7*Inputs!$F$10+Inputs!$E$14*Inputs!$F$15)*1000*Inputs!$F$22*Inputs!$F$23*Inputs!$F$24)*Inputs!$F$26*Inputs!$E$25)/(Inputs!$E$28+Inputs!$E$29+Inputs!$E$30*((Inputs!$E$9*Inputs!$F$6+Inputs!$F$7*Inputs!$F$10+Inputs!$E$14*Inputs!$F$15)*1000*Inputs!$F$22*Inputs!$F$23*Inputs!$F$24)) -> 3.6964037
A35: The low scenario sets every uncertain input to its low value at once, so it is a deliberately harsh stress test.

Sheet Sensitivity
A1: Sensitivity: what moves GoPro's value per £1?
A2: Each input moved to its Low and High value while all others stay at Base.
A3: Base value per £1: | D3: =Deal_Structure!B16 -> 2.1728936
A4: Input | B4: Low | C4: High | D4: Value per £1 at low | E4: Value per £1 at high | F4: Change at low | G4: Change at high | H4: Swing
A5: =Inputs!B24 -> Average order value | B5: =Inputs!$D$24 -> 250 | C5: =Inputs!$F$24 -> 400 | D5: =((Inputs!$E$9*Inputs!$E$6*Inputs!$E$18*Inputs!$E$17+Inputs!$E$7*Inputs!$E$18*Inputs!$E$17*Inputs!$E$11*Inputs!$E$10+Inputs!$E$12*Inputs!$E$13*Inputs!$E$20+Inputs!$E$14*Inputs!$E$15*Inputs!$E$18*Inputs!$E$17)+((Inputs!$E$9*Inputs!$E$6+Inputs!$E$7*Inputs!$E$10+Inputs!$E$14*Inputs!$E$15)*1000*Inputs!$E$22*Inputs!$E$23*$B5)*Inputs!$E$26*Inputs!$E$25)/(Inputs!$E$28+Inputs!$E$29+Inputs!$E$30*((Inputs!$E$9*Inputs!$E$6+Inputs!$E$7*Inputs!$E$10+Inputs!$E$14*Inputs!$E$15)*1000*Inputs!$E$22*Inputs!$E$23*$B5)) -> 2.168431 | E5: =((Inputs!$E$9*Inputs!$E$6*Inputs!$E$18*Inputs!$E$17+Inputs!$E$7*Inputs!$E$18*Inputs!$E$17*Inputs!$E$11*Inputs!$E$10+Inputs!$E$12*Inputs!$E$13*Inputs!$E$20+Inputs!$E$14*Inputs!$E$15*Inputs!$E$18*Inputs!$E$17)+((Inputs!$E$9*Inputs!$E$6+Inputs!$E$7*Inputs!$E$10+Inputs!$E$14*Inputs!$E$15)*1000*Inputs!$E$22*Inputs!$E$23*$C5)*Inputs!$E$26*Inputs!$E$25)/(Inputs!$E$28+Inputs!$E$29+Inputs!$E$30*((Inputs!$E$9*Inputs!$E$6+Inputs!$E$7*Inputs!$E$10+Inputs!$E$14*Inputs!$E$15)*1000*Inputs!$E$22*Inputs!$E$23*$C5)) -> 2.181198 | F5: =D5-$D$3 -> -0.0044625847 | G5: =E5-$D$3 -> 0.0083044339 | H5: =ABS(E5-D5) -> 0.012767019
A6: =Inputs!B23 -> Share of visitors who buy | B6: =Inputs!$D$23 -> 0.02 | C6: =Inputs!$F$23 -> 0.05 | D6: =((Inputs!$E$9*Inputs!$E$6*Inputs!$E$18*Inputs!$E$17+Inputs!$E$7*Inputs!$E$18*Inputs!$E$17*Inputs!$E$11*Inputs!$E$10+Inputs!$E$12*Inputs!$E$13*Inputs!$E$20+Inputs!$E$14*Inputs!$E$15*Inputs!$E$18*Inputs!$E$17)+((Inputs!$E$9*Inputs!$E$6+Inputs!$E$7*Inputs!$E$10+Inputs!$E$14*Inputs!$E$15)*1000*Inputs!$E$22*$B6*Inputs!$E$24)*Inputs!$E$26*Inputs!$E$25)/(Inputs!$E$28+Inputs!$E$29+Inputs!$E$30*((Inputs!$E$9*Inputs!$E$6+Inputs!$E$7*Inputs!$E$10+Inputs!$E$14*Inputs!$E$15)*1000*Inputs!$E$22*$B6*Inputs!$E$24)) -> 2.1637403 | E6: =((Inputs!$E$9*Inputs!$E$6*Inputs!$E$18*Inputs!$E$17+Inputs!$E$7*Inputs!$E$18*Inputs!$E$17*Inputs!$E$11*Inputs!$E$10+Inputs!$E$12*Inputs!$E$13*Inputs!$E$20+Inputs!$E$14*Inputs!$E$15*Inputs!$E$18*Inputs!$E$17)+((Inputs!$E$9*Inputs!$E$6+Inputs!$E$7*Inputs!$E$10+Inputs!$E$14*Inputs!$E$15)*1000*Inputs!$E$22*$C6*Inputs!$E$24)*Inputs!$E$26*Inputs!$E$25)/(Inputs!$E$28+Inputs!$E$29+Inputs!$E$30*((Inputs!$E$9*Inputs!$E$6+Inputs!$E$7*Inputs!$E$10+Inputs!$E$14*Inputs!$E$15)*1000*Inputs!$E$22*$C6*Inputs!$E$24)) -> 2.1887665 | F6: =D6-$D$3 -> -0.0091532296 | G6: =E6-$D$3 -> 0.015872906 | H6: =ABS(E6-D6) -> 0.025026136
A7: =Inputs!B22 -> Share of long-form/event views who visit via link or code | B7: =Inputs!$D$22 -> 0.001 | C7: =Inputs!$F$22 -> 0.004 | D7: =((Inputs!$E$9*Inputs!$E$6*Inputs!$E$18*Inputs!$E$17+Inputs!$E$7*Inputs!$E$18*Inputs!$E$17*Inputs!$E$11*Inputs!$E$10+Inputs!$E$12*Inputs!$E$13*Inputs!$E$20+Inputs!$E$14*Inputs!$E$15*Inputs!$E$18*Inputs!$E$17)+((Inputs!$E$9*Inputs!$E$6+Inputs!$E$7*Inputs!$E$10+Inputs!$E$14*Inputs!$E$15)*1000*$B7*Inputs!$E$23*Inputs!$E$24)*Inputs!$E$26*Inputs!$E$25)/(Inputs!$E$28+Inputs!$E$29+Inputs!$E$30*((Inputs!$E$9*Inputs!$E$6+Inputs!$E$7*Inputs!$E$10+Inputs!$E$14*Inputs!$E$15)*1000*$B7*Inputs!$E$23*Inputs!$E$24)) -> 2.1588037 | E7: =((Inputs!$E$9*Inputs!$E$6*Inputs!$E$18*Inputs!$E$17+Inputs!$E$7*Inputs!$E$18*Inputs!$E$17*Inputs!$E$11*Inputs!$E$10+Inputs!$E$12*Inputs!$E$13*Inputs!$E$20+Inputs!$E$14*Inputs!$E$15*Inputs!$E$18*Inputs!$E$17)+((Inputs!$E$9*Inputs!$E$6+Inputs!$E$7*Inputs!$E$10+Inputs!$E$14*Inputs!$E$15)*1000*$C7*Inputs!$E$23*Inputs!$E$24)*Inputs!$E$26*Inputs!$E$25)/(Inputs!$E$28+Inputs!$E$29+Inputs!$E$30*((Inputs!$E$9*Inputs!$E$6+Inputs!$E$7*Inputs!$E$10+Inputs!$E$14*Inputs!$E$15)*1000*$C7*Inputs!$E$23*Inputs!$E$24)) -> 2.1956927 | F7: =D7-$D$3 -> -0.014089876 | G7: =E7-$D$3 -> 0.022799099 | H7: =ABS(E7-D7) -> 0.036888975
A8: =Inputs!B15 -> Views per behind-the-scenes vlog | B8: =Inputs!$D$15 -> 2 | C8: =Inputs!$F$15 -> 4 | D8: =((Inputs!$E$9*Inputs!$E$6*Inputs!$E$18*Inputs!$E$17+Inputs!$E$7*Inputs!$E$18*Inputs!$E$17*Inputs!$E$11*Inputs!$E$10+Inputs!$E$12*Inputs!$E$13*Inputs!$E$20+Inputs!$E$14*$B8*Inputs!$E$18*Inputs!$E$17)+((Inputs!$E$9*Inputs!$E$6+Inputs!$E$7*Inputs!$E$10+Inputs!$E$14*$B8)*1000*Inputs!$E$22*Inputs!$E$23*Inputs!$E$24)*Inputs!$E$26*Inputs!$E$25)/(Inputs!$E$28+Inputs!$E$29+Inputs!$E$30*((Inputs!$E$9*Inputs!$E$6+Inputs!$E$7*Inputs!$E$10+Inputs!$E$14*$B8)*1000*Inputs!$E$22*Inputs!$E$23*Inputs!$E$24)) -> 2.092 | E8: =((Inputs!$E$9*Inputs!$E$6*Inputs!$E$18*Inputs!$E$17+Inputs!$E$7*Inputs!$E$18*Inputs!$E$17*Inputs!$E$11*Inputs!$E$10+Inputs!$E$12*Inputs!$E$13*Inputs!$E$20+Inputs!$E$14*$C8*Inputs!$E$18*Inputs!$E$17)+((Inputs!$E$9*Inputs!$E$6+Inputs!$E$7*Inputs!$E$10+Inputs!$E$14*$C8)*1000*Inputs!$E$22*Inputs!$E$23*Inputs!$E$24)*Inputs!$E$26*Inputs!$E$25)/(Inputs!$E$28+Inputs!$E$29+Inputs!$E$30*((Inputs!$E$9*Inputs!$E$6+Inputs!$E$7*Inputs!$E$10+Inputs!$E$14*$C8)*1000*Inputs!$E$22*Inputs!$E$23*Inputs!$E$24)) -> 2.2525215 | F8: =D8-$D$3 -> -0.080893561 | G8: =E8-$D$3 -> 0.079627951 | H8: =ABS(E8-D8) -> 0.16052151
A9: =Inputs!B7 -> Charity Match stream views | B9: =Inputs!$D$7 -> 8 | C9: =Inputs!$F$7 -> 14 | D9: =((Inputs!$E$9*Inputs!$E$6*Inputs!$E$18*Inputs!$E$17+$B9*Inputs!$E$18*Inputs!$E$17*Inputs!$E$11*Inputs!$E$10+Inputs!$E$12*Inputs!$E$13*Inputs!$E$20+Inputs!$E$14*Inputs!$E$15*Inputs!$E$18*Inputs!$E$17)+((Inputs!$E$9*Inputs!$E$6+$B9*Inputs!$E$10+Inputs!$E$14*Inputs!$E$15)*1000*Inputs!$E$22*Inputs!$E$23*Inputs!$E$24)*Inputs!$E$26*Inputs!$E$25)/(Inputs!$E$28+Inputs!$E$29+Inputs!$E$30*((Inputs!$E$9*Inputs!$E$6+$B9*Inputs!$E$10+Inputs!$E$14*Inputs!$E$15)*1000*Inputs!$E$22*Inputs!$E$23*Inputs!$E$24)) -> 2.0826015 | E9: =((Inputs!$E$9*Inputs!$E$6*Inputs!$E$18*Inputs!$E$17+$C9*Inputs!$E$18*Inputs!$E$17*Inputs!$E$11*Inputs!$E$10+Inputs!$E$12*Inputs!$E$13*Inputs!$E$20+Inputs!$E$14*Inputs!$E$15*Inputs!$E$18*Inputs!$E$17)+((Inputs!$E$9*Inputs!$E$6+$C9*Inputs!$E$10+Inputs!$E$14*Inputs!$E$15)*1000*Inputs!$E$22*Inputs!$E$23*Inputs!$E$24)*Inputs!$E$26*Inputs!$E$25)/(Inputs!$E$28+Inputs!$E$29+Inputs!$E$30*((Inputs!$E$9*Inputs!$E$6+$C9*Inputs!$E$10+Inputs!$E$14*Inputs!$E$15)*1000*Inputs!$E$22*Inputs!$E$23*Inputs!$E$24)) -> 2.2621241 | F9: =D9-$D$3 -> -0.090292107 | G9: =E9-$D$3 -> 0.089230541 | H9: =ABS(E9-D9) -> 0.17952265
A10: =Inputs!B26 -> Share of code sales that are incremental | B10: =Inputs!$D$26 -> 0.5 | C10: =Inputs!$F$26 -> 0.9 | D10: =((Inputs!$E$9*Inputs!$E$6*Inputs!$E$18*Inputs!$E$17+Inputs!$E$7*Inputs!$E$18*Inputs!$E$17*Inputs!$E$11*Inputs!$E$10+Inputs!$E$12*Inputs!$E$13*Inputs!$E$20+Inputs!$E$14*Inputs!$E$15*Inputs!$E$18*Inputs!$E$17)+((Inputs!$E$9*Inputs!$E$6+Inputs!$E$7*Inputs!$E$10+Inputs!$E$14*Inputs!$E$15)*1000*Inputs!$E$22*Inputs!$E$23*Inputs!$E$24)*$B10*Inputs!$E$25)/(Inputs!$E$28+Inputs!$E$29+Inputs!$E$30*((Inputs!$E$9*Inputs!$E$6+Inputs!$E$7*Inputs!$E$10+Inputs!$E$14*Inputs!$E$15)*1000*Inputs!$E$22*Inputs!$E$23*Inputs!$E$24)) -> 2.0748752 | E10: =((Inputs!$E$9*Inputs!$E$6*Inputs!$E$18*Inputs!$E$17+Inputs!$E$7*Inputs!$E$18*Inputs!$E$17*Inputs!$E$11*Inputs!$E$10+Inputs!$E$12*Inputs!$E$13*Inputs!$E$20+Inputs!$E$14*Inputs!$E$15*Inputs!$E$18*Inputs!$E$17)+((Inputs!$E$9*Inputs!$E$6+Inputs!$E$7*Inputs!$E$10+Inputs!$E$14*Inputs!$E$15)*1000*Inputs!$E$22*Inputs!$E$23*Inputs!$E$24)*$C10*Inputs!$E$25)/(Inputs!$E$28+Inputs!$E$29+Inputs!$E$30*((Inputs!$E$9*Inputs!$E$6+Inputs!$E$7*Inputs!$E$10+Inputs!$E$14*Inputs!$E$15)*1000*Inputs!$E$22*Inputs!$E$23*Inputs!$E$24)) -> 2.270912 | F10: =D10-$D$3 -> -0.098018397 | G10: =E10-$D$3 -> 0.098018397 | H10: =ABS(E10-D10) -> 0.19603679
A11: =Inputs!B11 -> Event premium for exclusivity, live reach and press | B11: =Inputs!$D$11 -> 1 | C11: =Inputs!$F$11 -> 2 | D11: =((Inputs!$E$9*Inputs!$E$6*Inputs!$E$18*Inputs!$E$17+Inputs!$E$7*Inputs!$E$18*Inputs!$E$17*$B11*Inputs!$E$10+Inputs!$E$12*Inputs!$E$13*Inputs!$E$20+Inputs!$E$14*Inputs!$E$15*Inputs!$E$18*Inputs!$E$17)+((Inputs!$E$9*Inputs!$E$6+Inputs!$E$7*Inputs!$E$10+Inputs!$E$14*Inputs!$E$15)*1000*Inputs!$E$22*Inputs!$E$23*Inputs!$E$24)*Inputs!$E$26*Inputs!$E$25)/(Inputs!$E$28+Inputs!$E$29+Inputs!$E$30*((Inputs!$E$9*Inputs!$E$6+Inputs!$E$7*Inputs!$E$10+Inputs!$E$14*Inputs!$E$15)*1000*Inputs!$E$22*Inputs!$E$23*Inputs!$E$24)) -> 2.0644836 | E11: =((Inputs!$E$9*Inputs!$E$6*Inputs!$E$18*Inputs!$E$17+Inputs!$E$7*Inputs!$E$18*Inputs!$E$17*$C11*Inputs!$E$10+Inputs!$E$12*Inputs!$E$13*Inputs!$E$20+Inputs!$E$14*Inputs!$E$15*Inputs!$E$18*Inputs!$E$17)+((Inputs!$E$9*Inputs!$E$6+Inputs!$E$7*Inputs!$E$10+Inputs!$E$14*Inputs!$E$15)*1000*Inputs!$E$22*Inputs!$E$23*Inputs!$E$24)*Inputs!$E$26*Inputs!$E$25)/(Inputs!$E$28+Inputs!$E$29+Inputs!$E$30*((Inputs!$E$9*Inputs!$E$6+Inputs!$E$7*Inputs!$E$10+Inputs!$E$14*Inputs!$E$15)*1000*Inputs!$E$22*Inputs!$E$23*Inputs!$E$24)) -> 2.2813035 | F11: =D11-$D$3 -> -0.10840999 | G11: =E11-$D$3 -> 0.10840999 | H11: =ABS(E11-D11) -> 0.21681997
A12: =Inputs!B20 -> Short-form CPM (£ per 1,000 views) | B12: =Inputs!$D$20 -> 2 | C12: =Inputs!$F$20 -> 6 | D12: =((Inputs!$E$9*Inputs!$E$6*Inputs!$E$18*Inputs!$E$17+Inputs!$E$7*Inputs!$E$18*Inputs!$E$17*Inputs!$E$11*Inputs!$E$10+Inputs!$E$12*Inputs!$E$13*$B12+Inputs!$E$14*Inputs!$E$15*Inputs!$E$18*Inputs!$E$17)+((Inputs!$E$9*Inputs!$E$6+Inputs!$E$7*Inputs!$E$10+Inputs!$E$14*Inputs!$E$15)*1000*Inputs!$E$22*Inputs!$E$23*Inputs!$E$24)*Inputs!$E$26*Inputs!$E$25)/(Inputs!$E$28+Inputs!$E$29+Inputs!$E$30*((Inputs!$E$9*Inputs!$E$6+Inputs!$E$7*Inputs!$E$10+Inputs!$E$14*Inputs!$E$15)*1000*Inputs!$E$22*Inputs!$E$23*Inputs!$E$24)) -> 2.0414875 | E12: =((Inputs!$E$9*Inputs!$E$6*Inputs!$E$18*Inputs!$E$17+Inputs!$E$7*Inputs!$E$18*Inputs!$E$17*Inputs!$E$11*Inputs!$E$10+Inputs!$E$12*Inputs!$E$13*$C12+Inputs!$E$14*Inputs!$E$15*Inputs!$E$18*Inputs!$E$17)+((Inputs!$E$9*Inputs!$E$6+Inputs!$E$7*Inputs!$E$10+Inputs!$E$14*Inputs!$E$15)*1000*Inputs!$E$22*Inputs!$E$23*Inputs!$E$24)*Inputs!$E$26*Inputs!$E$25)/(Inputs!$E$28+Inputs!$E$29+Inputs!$E$30*((Inputs!$E$9*Inputs!$E$6+Inputs!$E$7*Inputs!$E$10+Inputs!$E$14*Inputs!$E$15)*1000*Inputs!$E$22*Inputs!$E$23*Inputs!$E$24)) -> 2.3042996 | F12: =D12-$D$3 -> -0.13140604 | G12: =E12-$D$3 -> 0.13140604 | H12: =ABS(E12-D12) -> 0.26281209
A13: =Inputs!B10 -> GoPro prominence in Charity Match stream | B13: =Inputs!$D$10 -> 0.3 | C13: =Inputs!$F$10 -> 0.7 | D13: =((Inputs!$E$9*Inputs!$E$6*Inputs!$E$18*Inputs!$E$17+Inputs!$E$7*Inputs!$E$18*Inputs!$E$17*Inputs!$E$11*$B13+Inputs!$E$12*Inputs!$E$13*Inputs!$E$20+Inputs!$E$14*Inputs!$E$15*Inputs!$E$18*Inputs!$E$17)+((Inputs!$E$9*Inputs!$E$6+Inputs!$E$7*$B13+Inputs!$E$14*Inputs!$E$15)*1000*Inputs!$E$22*Inputs!$E$23*Inputs!$E$24)*Inputs!$E$26*Inputs!$E$25)/(Inputs!$E$28+Inputs!$E$29+Inputs!$E$30*((Inputs!$E$9*Inputs!$E$6+Inputs!$E$7*$B13+Inputs!$E$14*Inputs!$E$15)*1000*Inputs!$E$22*Inputs!$E$23*Inputs!$E$24)) -> 2.0400965 | E13: =((Inputs!$E$9*Inputs!$E$6*Inputs!$E$18*Inputs!$E$17+Inputs!$E$7*Inputs!$E$18*Inputs!$E$17*Inputs!$E$11*$C13+Inputs!$E$12*Inputs!$E$13*Inputs!$E$20+Inputs!$E$14*Inputs!$E$15*Inputs!$E$18*Inputs!$E$17)+((Inputs!$E$9*Inputs!$E$6+Inputs!$E$7*$C13+Inputs!$E$14*Inputs!$E$15)*1000*Inputs!$E$22*Inputs!$E$23*Inputs!$E$24)*Inputs!$E$26*Inputs!$E$25)/(Inputs!$E$28+Inputs!$E$29+Inputs!$E$30*((Inputs!$E$9*Inputs!$E$6+Inputs!$E$7*$C13+Inputs!$E$14*Inputs!$E$15)*1000*Inputs!$E$22*Inputs!$E$23*Inputs!$E$24)) -> 2.303407 | F13: =D13-$D$3 -> -0.13279706 | G13: =E13-$D$3 -> 0.13051342 | H13: =ABS(E13-D13) -> 0.26331048
A14: =Inputs!B13 -> Views per short-form clip | B14: =Inputs!$D$13 -> 0.8 | C14: =Inputs!$F$13 -> 2.5 | D14: =((Inputs!$E$9*Inputs!$E$6*Inputs!$E$18*Inputs!$E$17+Inputs!$E$7*Inputs!$E$18*Inputs!$E$17*Inputs!$E$11*Inputs!$E$10+Inputs!$E$12*$B14*Inputs!$E$20+Inputs!$E$14*Inputs!$E$15*Inputs!$E$18*Inputs!$E$17)+((Inputs!$E$9*Inputs!$E$6+Inputs!$E$7*Inputs!$E$10+Inputs!$E$14*Inputs!$E$15)*1000*Inputs!$E$22*Inputs!$E$23*Inputs!$E$24)*Inputs!$E$26*Inputs!$E$25)/(Inputs!$E$28+Inputs!$E$29+Inputs!$E$30*((Inputs!$E$9*Inputs!$E$6+Inputs!$E$7*Inputs!$E$10+Inputs!$E$14*Inputs!$E$15)*1000*Inputs!$E$22*Inputs!$E$23*Inputs!$E$24)) -> 2.0502479 | E14: =((Inputs!$E$9*Inputs!$E$6*Inputs!$E$18*Inputs!$E$17+Inputs!$E$7*Inputs!$E$18*Inputs!$E$17*Inputs!$E$11*Inputs!$E$10+Inputs!$E$12*$C14*Inputs!$E$20+Inputs!$E$14*Inputs!$E$15*Inputs!$E$18*Inputs!$E$17)+((Inputs!$E$9*Inputs!$E$6+Inputs!$E$7*Inputs!$E$10+Inputs!$E$14*Inputs!$E$15)*1000*Inputs!$E$22*Inputs!$E$23*Inputs!$E$24)*Inputs!$E$26*Inputs!$E$25)/(Inputs!$E$28+Inputs!$E$29+Inputs!$E$30*((Inputs!$E$9*Inputs!$E$6+Inputs!$E$7*Inputs!$E$10+Inputs!$E$14*Inputs!$E$15)*1000*Inputs!$E$22*Inputs!$E$23*Inputs!$E$24)) -> 2.3481016 | F14: =D14-$D$3 -> -0.12264564 | G14: =E14-$D$3 -> 0.17520806 | H14: =ABS(E14-D14) -> 0.2978537
A15: =Inputs!B6 -> Sidemen main-channel views per video (recent median) | B15: =Inputs!$D$6 -> 6 | C15: =Inputs!$F$6 -> 12 | D15: =((Inputs!$E$9*$B15*Inputs!$E$18*Inputs!$E$17+Inputs!$E$7*Inputs!$E$18*Inputs!$E$17*Inputs!$E$11*Inputs!$E$10+Inputs!$E$12*Inputs!$E$13*Inputs!$E$20+Inputs!$E$14*Inputs!$E$15*Inputs!$E$18*Inputs!$E$17)+((Inputs!$E$9*$B15+Inputs!$E$7*Inputs!$E$10+Inputs!$E$14*Inputs!$E$15)*1000*Inputs!$E$22*Inputs!$E$23*Inputs!$E$24)*Inputs!$E$26*Inputs!$E$25)/(Inputs!$E$28+Inputs!$E$29+Inputs!$E$30*((Inputs!$E$9*$B15+Inputs!$E$7*Inputs!$E$10+Inputs!$E$14*Inputs!$E$15)*1000*Inputs!$E$22*Inputs!$E$23*Inputs!$E$24)) -> 1.8627651 | E15: =((Inputs!$E$9*$C15*Inputs!$E$18*Inputs!$E$17+Inputs!$E$7*Inputs!$E$18*Inputs!$E$17*Inputs!$E$11*Inputs!$E$10+Inputs!$E$12*Inputs!$E$13*Inputs!$E$20+Inputs!$E$14*Inputs!$E$15*Inputs!$E$18*Inputs!$E$17)+((Inputs!$E$9*$C15+Inputs!$E$7*Inputs!$E$10+Inputs!$E$14*Inputs!$E$15)*1000*Inputs!$E$22*Inputs!$E$23*Inputs!$E$24)*Inputs!$E$26*Inputs!$E$25)/(Inputs!$E$28+Inputs!$E$29+Inputs!$E$30*((Inputs!$E$9*$C15+Inputs!$E$7*Inputs!$E$10+Inputs!$E$14*Inputs!$E$15)*1000*Inputs!$E$22*Inputs!$E$23*Inputs!$E$24)) -> 2.577489 | F15: =D15-$D$3 -> -0.3101285 | G15: =E15-$D$3 -> 0.4045954 | H15: =ABS(E15-D15) -> 0.71472389
A16: =Inputs!B18 -> Long-form sponsorship CPM (US$ per 1,000 views) | B16: =Inputs!$D$18 -> 15 | C16: =Inputs!$F$18 -> 30 | D16: =((Inputs!$E$9*Inputs!$E$6*$B16*Inputs!$E$17+Inputs!$E$7*$B16*Inputs!$E$17*Inputs!$E$11*Inputs!$E$10+Inputs!$E$12*Inputs!$E$13*Inputs!$E$20+Inputs!$E$14*Inputs!$E$15*$B16*Inputs!$E$17)+((Inputs!$E$9*Inputs!$E$6+Inputs!$E$7*Inputs!$E$10+Inputs!$E$14*Inputs!$E$15)*1000*Inputs!$E$22*Inputs!$E$23*Inputs!$E$24)*Inputs!$E$26*Inputs!$E$25)/(Inputs!$E$28+Inputs!$E$29+Inputs!$E$30*((Inputs!$E$9*Inputs!$E$6+Inputs!$E$7*Inputs!$E$10+Inputs!$E$14*Inputs!$E$15)*1000*Inputs!$E$22*Inputs!$E$23*Inputs!$E$24)) -> 1.5852622 | E16: =((Inputs!$E$9*Inputs!$E$6*$C16*Inputs!$E$17+Inputs!$E$7*$C16*Inputs!$E$17*Inputs!$E$11*Inputs!$E$10+Inputs!$E$12*Inputs!$E$13*Inputs!$E$20+Inputs!$E$14*Inputs!$E$15*$C16*Inputs!$E$17)+((Inputs!$E$9*Inputs!$E$6+Inputs!$E$7*Inputs!$E$10+Inputs!$E$14*Inputs!$E$15)*1000*Inputs!$E$22*Inputs!$E$23*Inputs!$E$24)*Inputs!$E$26*Inputs!$E$25)/(Inputs!$E$28+Inputs!$E$29+Inputs!$E$30*((Inputs!$E$9*Inputs!$E$6+Inputs!$E$7*Inputs!$E$10+Inputs!$E$14*Inputs!$E$15)*1000*Inputs!$E$22*Inputs!$E$23*Inputs!$E$24)) -> 2.5646478 | F16: =D16-$D$3 -> -0.58763141 | G16: =E16-$D$3 -> 0.39175427 | H16: =ABS(E16-D16) -> 0.97938568
A18: Rows ordered by swing (smallest first) so the biggest driver sits at the top of the tornado chart.

Sheet Upside
A1: Upside portfolio: which companies should get Sidemen airtime, and how?
A2: Upside makes Sidemen inventory available to portfolio companies free of charge, so the cost is the income that airtime could have earned from a paying brand. Customer and value inputs are illustrative assumptions to replace with each company's data.
B4: Howbout | C4: Nimbi | D4: Ceartas | E4: Notes
A5: What it does | B5: Social calendar app for planning with friends | C5: Plastic-free razor (RRP $1.50) | D5: AI copyright and piracy protection for creators | E5: Public sources: TechCrunch 2024; FounderMade; Silicon Republic 2024
A6: Stage and scale | B6: 4m+ users; majority aged 25 or under; $8m Series A (2024) | C6: Early-stage consumer brand | D6: $4.5m seed co-led by Upside (2024)
A7: Proposed integration | B7: Charity Match watch-party planner + 'plan a Sidemen Sunday' shorts | C7: Changing-room segment in a match-day vlog + shorts | D7: Protect the Charity Match stream from piracy; behind-the-scenes segment | E7: Placed in cheaper inventory: shorts, vlogs, event moments
A9: Scorecard (same weights as brand scorecard) | F9: Weight
A10: Audience fit (18-25, UK) | B10: 5 | C10: 3 | D10: 2 | F10: =Scorecard!B$4 -> 0.2
A11: Fits naturally in videos and events | B11: 4 | C11: 3 | D11: 2 | F11: =Scorecard!C$4 -> 0.25
A12: No clash with Sidemen or member brands | B12: 5 | C12: 5 | D12: 5 | F12: =Scorecard!D$4 -> 0.15
A13: Freshness: not overused by UK creators | B13: 4 | C13: 5 | D13: 5 | F13: =Scorecard!E$4 -> 0.15
A14: Brand safety and sentiment | B14: 4 | C14: 4 | D14: 4 | F14: =Scorecard!F$4 -> 0.1
A15: Commercial need: why now | B15: 4 | C15: 4 | D15: 3 | F15: =Scorecard!G$4 -> 0.15
A16: Weighted score (out of 5) | B16: =SUMPRODUCT($F$10:$F$15,B10:B15) -> 4.35 | C16: =SUMPRODUCT($F$10:$F$15,C10:C15) -> 3.85 | D16: =SUMPRODUCT($F$10:$F$15,D10:D15) -> 3.25
A18: Value of airtime (inputs in blue)
A19: Long-form / event views allocated (m) | B19: 3 | C19: 2 | D19: 1 | E19: Event mentions are prominence-adjusted views
A20: Short-form views allocated (m) | B20: 15 | C20: 6 | D20: 0
A21: Share of viewers who visit or install | B21: 0.004 | C21: 0.0015 | D21: 0.0005 | E21: Assumption: free app install is low-friction; razor and B2B service much less so
A22: Share of visitors who become customers or users | B22: 0.4 | C22: 0.08 | D22: 0.03
A23: Value per customer (£) | B23: 4 | C23: 15 | D23: 400 | E23: Howbout: app install cost avoided; Nimbi: first-year gross profit; Ceartas: annual subscription (all assumptions)
A25: Customers or users gained | B25: =(B19+B20)*1000000*B21*B22 -> 28800 | C25: =(C19+C20)*1000000*C21*C22 -> 960 | D25: =(D19+D20)*1000000*D21*D22 -> 15
A26: Value created for the company (£k) | B26: =B25*B23/1000 -> 115.2 | C26: =C25*C23/1000 -> 14.4 | D26: =D25*D23/1000 -> 6
A27: Cost: income the airtime could earn from a paying brand (£k) | B27: =B19*Inputs!$E$19+B20*Inputs!$E$20 -> 114 | C27: =C19*Inputs!$E$19+C20*Inputs!$E$20 -> 60 | D27: =D19*Inputs!$E$19+D20*Inputs!$E$20 -> 18
A28: Value created per £1 of airtime | B28: =IFERROR(B26/B27,0) -> 1.0105263 | C28: =IFERROR(C26/C27,0) -> 0.24 | D28: =IFERROR(D26/D27,0) -> 0.33333333
A29: Effective cost per customer (£) | B29: =IFERROR(B27*1000/B25,0) -> 3.9583333 | C29: =IFERROR(C27*1000/C25,0) -> 62.5 | D29: =IFERROR(D27*1000/D25,0) -> 1200
A31: Recommended approach
A32: Howbout | B32: Priority 1. Highest score and best value per £ of airtime: a free app that fits how Sidemen fans already plan watch-parties and meet-ups. Use event moments and shorts, not main-video slots.
A33: Nimbi | B33: Priority 2. Low-cost inventory only (shorts, vlog segments). A low-price product needs many buyers, so main-video airtime would cost more than it creates.
A34: Ceartas | B34: Use it, don't advertise it. Its customers are creators, not fans, so views barely convert. Better value: protect the Charity Match stream and clips from piracy, then publish the results as a case study.

Sheet Sources
A1: Sources
A3: # | B3: Used for | C3: Reference | D3: Link
A4: 1 | B4: Sidemen channel: 23.4m subscribers, 51.9m views in 28 days, 515 videos | C4: vidIQ channel stats (Oct 2026) | D4: https://vidiq.com/youtube-stats/channel/@sidemen/
A5: 2 | B5: Recent outlier videos and their multiple of the recent median | C5: OutlierKit channel analysis | D5: https://outlierkit.com/channel/sidemen
A6: 3 | B6: Charity Match views, live viewers, attendance and money raised (2025, 2026) | C6: Wikipedia, Sidemen Charity Match | D6: https://en.wikipedia.org/wiki/Sidemen_Charity_Match
A7: 4 | B7: 2026 Charity Match: over 11m views, peak 2.2m concurrent, £6.2m raised | C7: Tubefilter (Apr 2026) | D7: https://www.tubefilter.com/2026/04/20/sidemen-charity-soccer-football-match-2026-results-highlights/
A8: 5 | B8: 2025 Charity Match peak of 2.5m concurrent viewers, £4.7m raised | C8: Tubefilter (Mar 2025) | D8: https://www.tubefilter.com/?p=185173
A9: 6 | B9: FotMob and Opta as 2025 Charity Match partners | C9: Mobile Marketing Magazine | D9: https://mobilemarketingmagazine.com/?p=126104
A10: 7 | B10: YouTube sponsorship CPM of $15-30 | C10: Influencer Marketing Hub, YouTube Influencer Rates (2026) | D10: https://influencermarketinghub.com/youtube-influencer-rates
A11: 8 | B11: GoPro FY2025 revenue, gross margin, sales & marketing, units, subscribers | C11: GoPro Q4 and FY2025 results (Mar 2026) | D11: https://investor.gopro.com/press-releases/press-release-details/2026/GoPro-Announces-Fourth-Quarter-and-2025-Results/
A12: 9 | B12: Marketing spend cut 37%; influencer and athlete marketing approach | C12: GoPro Form 10-K FY2025 | D12: https://www.sec.gov/Archives/edgar/data/1500435/000150043526000006/gpro-20251231.htm
A13: 10 | B13: GoPro Q3 2025 revenue down 37%; turnaround strategy | C13: Bicycle Retailer (Nov 2025) | D13: https://bicycleretailer.com/industry-news/2025/11/07/retail-and-online-sales-dip-overall-gopro-revenue-declines-37-year-over
A14: 11 | B14: GoPro HERO13 Black UK prices | C14: PriceSpy UK | D14: https://pricespy.co.uk/s/gopro-13-black/
A15: 12 | B15: Upside fund, partners and use of Sidemen promotion | C15: Tubefilter (May 2025) | D15: https://www.tubefilter.com/2025/05/15/sidemen-venture-capital-firm-upside-invest-creator-economy/
... A22: 19 | B22: Whoop official supplier to British & Irish Lions (2025) | C22: Whoop press centre | D22: https://www.whoop.com/us/en/press-center/whoop-r-joins-the-british-and-irish-lions-as-official-supplier-for-the-qatar/
